react_comments_django/__init__.py
react_comments_django/admin.py
react_comments_django/apis.py
react_comments_django/apps.py
react_comments_django/context_processors.py
react_comments_django/forms.py
react_comments_django/meta_badges.py
react_comments_django/models.py
react_comments_django/permissions.py
react_comments_django/serializers.py
react_comments_django/sitemaps.py
react_comments_django/urls_api.py
react_comments_django/migrations/0001_initial.py
react_comments_django/migrations/__init__.py
react_comments_django/templatetags/__init__.py
react_comments_django/tests/__init__.py
react_comments_django/tests/test_models.py
react_comments_django/utils/__init__.py
react_comments_django/utils/base_tests.py
react_comments_django/utils/utility_funcs.py
react_comments_django-1.0.2.dist-info/AUTHORS.rst
react_comments_django-1.0.2.dist-info/LICENSE
react_comments_django-1.0.2.dist-info/METADATA
react_comments_django-1.0.2.dist-info/WHEEL
react_comments_django-1.0.2.dist-info/top_level.txt
react_comments_django-1.0.2.dist-info/RECORD
