Metadata-Version: 2.1
Name: react-comments-django
Version: 1.0.2
Summary: React Django forum/comments application with Reddit like features
Home-page: https://github.com/studyhub-co/react-comments-django
Author: studyhub.co
Author-email: nscozzaro@gmail.com
License: Apache Software License 2.0
Keywords: react-comments-django
Platform: UNKNOWN
Classifier: Development Status :: 3 - Alpha
Classifier: Framework :: Django
Classifier: Framework :: Django :: 1.8
Classifier: Framework :: Django :: 1.9
Classifier: Framework :: Django :: 1.10
Classifier: Intended Audience :: Developers
Classifier: License :: OSI Approved :: BSD License
Classifier: Natural Language :: English
Classifier: Programming Language :: Python :: 2
Classifier: Programming Language :: Python :: 2.7
Classifier: Programming Language :: Python :: 3
Classifier: Programming Language :: Python :: 3.3
Classifier: Programming Language :: Python :: 3.4
Classifier: Programming Language :: Python :: 3.5
Requires-Dist: django-crispy-forms (>=1.6.1)
Requires-Dist: django-mptt (>=0.8.7)
Requires-Dist: awesome-slugify (>=1.6.5)
Requires-Dist: django-ipware (>=2.1.0)
Requires-Dist: django-meta (>=1.4.1)
